codebox/__init__.py
codebox/codebox.py
codebox/python_syntax_highlighter.py
nova_codebox-1.4.dist-info/LICENSE
nova_codebox-1.4.dist-info/METADATA
nova_codebox-1.4.dist-info/WHEEL
nova_codebox-1.4.dist-info/top_level.txt
nova_codebox-1.4.dist-info/RECORD
