Metadata-Version: 2.1
Name: nova-codebox
Version: 1.4
Summary: Eine CodeBox-Komponente für PyQt5
Home-page: https://github.com/NovaPorta/PyQT5-Codebox/
Author: NovaPorta
Author-email: info@novaporta.de
Classifier: Programming Language :: Python :: 3
Classifier: License :: OSI Approved :: MIT License
Classifier: Operating System :: OS Independent
Requires-Python: >=3.6
License-File: LICENSE
Requires-Dist: PyQt5>=5.15
